{
  "name": "ble-scanner",
  "version": "2.1.0",
  "description": "Generic BleScanner using NimBle listening to advertisements. IDF component variant.",
  "keywords": [
    "ble",
    "esp32",
    "scanner",
    "nimble",
    "espidf",
    "espressif"
  ],
  "license": "GPL-3.0",
  "authors": [
    {
      "name": "Jeroen van de Vorst",
      "maintainer": true
    },
    {
      "name": "Bas Schouten"
    }
  ],
  "repository": {
    "type": "git",
    "url": "https://github.com/AzonInc/ble-scanner"
  }
}

